Workbook

Sheet Proforma 24mo
A1: LINE \ MONTH | B1: M1 | C1: M2 | D1: M3 | E1: M4 | F1: M5 | G1: M6 | H1: M7 | I1: M8 | J1: M9 | K1: M10 | L1: M11 | M1: M12 | N1: M13 | O1: M14 | P1: M15 | Q1: M16 | R1: M17 | S1: M18 | T1: M19 | U1: M20 | V1: M21 | W1: M22 | X1: M23 | Y1: M24
A3: Co-build client revenue | B3: =ROUND((Assumptions!$C$9*Assumptions!$C$8/12)*0.2,0) | C3: =ROUND((Assumptions!$C$9*Assumptions!$C$8/12)*0.2,0) | D3: =ROUND((Assumptions!$C$9*Assumptions!$C$8/12)*0.2,0) | E3: =ROUND((Assumptions!$C$9*Assumptions!$C$8/12)*0.2,0) | F3: =ROUND((Assumptions!$C$9*Assumptions!$C$8/12)*0.2,0) | G3: =ROUND((Assumptions!$C$9*Assumptions!$C$8/12)*0.2,0) | H3: =ROUND((Assumptions!$C$9*Assumptions!$C$8/12)*0.5,0) | I3: =ROUND((Assumptions!$C$9*Assumptions!$C$8/12)*0.5,0) | J3: =ROUND((Assumptions!$C$9*Assumptions!$C$8/12)*0.5,0) | K3: =ROUND((Assumptions!$C$9*Assumptions!$C$8/12)*0.5,0) | L3: =ROUND((Assumptions!$C$9*Assumptions!$C$8/12)*0.5,0) | M3: =ROUND((Assumptions!$C$9*Assumptions!$C$8/12)*0.5,0) | N3: =ROUND(Assumptions!$C$12*Assumptions!$C$11/12,0) | O3: =ROUND(Assumptions!$C$12*Assumptions!$C$11/12,0) | P3: =ROUND(Assumptions!$C$12*Assumptions!$C$11/12,0) | Q3: =ROUND(Assumptions!$C$12*Assumptions!$C$11/12,0) | R3: =ROUND(Assumptions!$C$12*Assumptions!$C$11/12,0) | S3: =ROUND(Assumptions!$C$12*Assumptions!$C$11/12,0) | T3: =ROUND(Assumptions!$C$12*Assumptions!$C$11/12,0) | U3: =ROUND(Assumptions!$C$12*Assumptions!$C$11/12,0) | ... Y3: =ROUND(Assumptions!$C$12*Assumptions!$C$11/12,0)
A4: Hosted SaaS revenue | B4: =Assumptions!$C$10*Assumptions!$C$6 | C4: =Assumptions!$C$10*Assumptions!$C$6 | D4: =Assumptions!$C$10*Assumptions!$C$6 | E4: =Assumptions!$C$10*Assumptions!$C$6 | F4: =Assumptions!$C$10*Assumptions!$C$6 | G4: =Assumptions!$C$10*Assumptions!$C$6 | H4: =Assumptions!$C$10*Assumptions!$C$6 | I4: =Assumptions!$C$10*Assumptions!$C$6 | ... M4: =Assumptions!$C$10*Assumptions!$C$6 | N4: =Assumptions!$C$13*Assumptions!$C$6 | O4: =Assumptions!$C$13*Assumptions!$C$6 | P4: =Assumptions!$C$13*Assumptions!$C$6 | Q4: =Assumptions!$C$13*Assumptions!$C$6 | R4: =Assumptions!$C$13*Assumptions!$C$6 | S4: =Assumptions!$C$13*Assumptions!$C$6 | T4: =Assumptions!$C$13*Assumptions!$C$6 | U4: =Assumptions!$C$13*Assumptions!$C$6 | ... Y4: =Assumptions!$C$13*Assumptions!$C$6
A5: White-label revenue | B5: =Assumptions!$C$14*Assumptions!$C$7 | C5: =Assumptions!$C$14*Assumptions!$C$7 | D5: =Assumptions!$C$14*Assumptions!$C$7 | E5: =Assumptions!$C$14*Assumptions!$C$7 | F5: =Assumptions!$C$14*Assumptions!$C$7 | G5: =Assumptions!$C$14*Assumptions!$C$7 | H5: =Assumptions!$C$14*Assumptions!$C$7 | I5: =Assumptions!$C$14*Assumptions!$C$7 | ... Y5: =Assumptions!$C$14*Assumptions!$C$7
A6: TOTAL REVENUE | B6: =SUM(B3:B5) | C6: =SUM(C3:C5) | D6: =SUM(D3:D5) | E6: =SUM(E3:E5) | F6: =SUM(F3:F5) | G6: =SUM(G3:G5) | H6: =SUM(H3:H5) | I6: =SUM(I3:I5) | ... Y6: =SUM(Y3:Y5)
A7: Costs
A8: Model/API + GPU | B8: =Assumptions!$C$15 | C8: =Assumptions!$C$15 | D8: =Assumptions!$C$15 | E8: =Assumptions!$C$15 | F8: =Assumptions!$C$15 | G8: =Assumptions!$C$15 | H8: =Assumptions!$C$15 | I8: =Assumptions!$C$15 | ... Y8: =Assumptions!$C$15
A9: Founder draw | B9: =Assumptions!$C$16 | C9: =Assumptions!$C$16 | D9: =Assumptions!$C$16 | E9: =Assumptions!$C$16 | F9: =Assumptions!$C$16 | G9: =Assumptions!$C$16 | H9: =Assumptions!$C$16 | I9: =Assumptions!$C$16 | ... Y9: =Assumptions!$C$16
A10: Infra | B10: =Assumptions!$C$17 | C10: =Assumptions!$C$17 | D10: =Assumptions!$C$17 | E10: =Assumptions!$C$17 | F10: =Assumptions!$C$17 | G10: =Assumptions!$C$17 | H10: =Assumptions!$C$17 | I10: =Assumptions!$C$17 | ... Y10: =Assumptions!$C$17
A11: Mktg & sales | B11: =Assumptions!$C$18 | C11: =Assumptions!$C$18 | D11: =Assumptions!$C$18 | E11: =Assumptions!$C$18 | F11: =Assumptions!$C$18 | G11: =Assumptions!$C$18 | H11: =Assumptions!$C$18 | I11: =Assumptions!$C$18 | ... Y11: =Assumptions!$C$18
A12: Legal/acctg | B12: =Assumptions!$C$19 | C12: =Assumptions!$C$19 | D12: =Assumptions!$C$19 | E12: =Assumptions!$C$19 | F12: =Assumptions!$C$19 | G12: =Assumptions!$C$19 | H12: =Assumptions!$C$19 | I12: =Assumptions!$C$19 | ... Y12: =Assumptions!$C$19
A13: TOTAL COSTS | B13: =SUM(B8:B12) | C13: =SUM(C8:C12) | D13: =SUM(D8:D12) | E13: =SUM(E8:E12) | F13: =SUM(F8:F12) | G13: =SUM(G8:G12) | H13: =SUM(H8:H12) | I13: =SUM(I8:I12) | ... Y13: =SUM(Y8:Y12)
A14: NET (pre-tax) | B14: =B6-B13 | C14: =C6-C13 | D14: =D6-D13 | E14: =E6-E13 | F14: =F6-F13 | G14: =G6-G13 | H14: =H6-H13 | I14: =I6-I13 | ... Y14: =Y6-Y13
A15: NET (post-tax) | B15: =ROUND(B14*(1-Assumptions!$C$20),0) | C15: =ROUND(C14*(1-Assumptions!$C$20),0) | D15: =ROUND(D14*(1-Assumptions!$C$20),0) | E15: =ROUND(E14*(1-Assumptions!$C$20),0) | F15: =ROUND(F14*(1-Assumptions!$C$20),0) | G15: =ROUND(G14*(1-Assumptions!$C$20),0) | H15: =ROUND(H14*(1-Assumptions!$C$20),0) | I15: =ROUND(I14*(1-Assumptions!$C$20),0) | ... Y15: =ROUND(Y14*(1-Assumptions!$C$20),0)

Sheet Assumptions
A1: ENI ENTERPRISE — PROFORMA ASSUMPTIONS (edit the YELLOW cells; every other cell is a live formula)
A2: Item | B2: key | C2: value
A4: Team license ARR, low | B4: team_annual_low | C4: 12000
A5: Team license ARR, high | B5: team_annual_high | C5: 25000
A6: Hosted SaaS per builder/mo | B6: saas_builder_mo | C6: 10
A7: White-label margin % | B7: white_margin | C7: 0.4
A8: Y1 avg co-build clients | B8: y1_clients | C8: 2
A9: Y1 avg $/client/yr | B9: y1_arpu | C9: 15000
A10: Y1 hosted builders (avg) | B10: y1_builders | C10: 8
A11: Y2 avg co-build clients | B11: y2_clients | C11: 5
A12: Y2 avg $/client/yr | B12: y2_arpu | C12: 16000
A13: Y2 hosted builders (avg) | B13: y2_builders | C13: 20
A14: White-label $/session | B14: white_per_session | C14: 1500
A15: Model/API + GPU /month | B15: cost_model | C15: 800
... A20: Tax rate | B20: tax_rate | C20: 0.2

Sheet Yearly Summary
A1: YEARLY SUMMARY
A2: Year | B2: Revenue | C2: Costs | D2: Net (pre) | E2: Net (post)
A3: Year 1 | B3: =C6+D6+E6+F6+G6+H6+I6+J6+K6+L6+M6+N6 | C3: =C13+D13+E13+F13+G13+H13+I13+J13+K13+L13+M13+N13 | D3: =C14+D14+E14+F14+G14+H14+I14+J14+K14+L14+M14+N14 | E3: =C15+D15+E15+F15+G15+H15+I15+J15+K15+L15+M15+N15
A4: Year 2 | B4: =O6+P6+Q6+R6+S6+T6+U6+V6+W6+X6+Y6+Z6 | C4: =O13+P13+Q13+R13+S13+T13+U13+V13+W13+X13+Y13+Z13 | D4: =O14+P14+Q14+R14+S14+T14+U14+V14+W14+X14+Y14+Z14 | E4: =O15+P15+Q15+R15+S15+T15+U15+V15+W15+X15+Y15+Z15
